minkar/__init__.py
minkar/cli.py
minkar/cmd/__init__.py
minkar/cmd/cmd.py
minkar/get/__init__.py
minkar/get/code.py
minkar/get/dir.py
minkar/get/file.py
minkar-0.3.2.dist-info/licenses/LICENSE.md
minkar-0.3.2.dist-info/METADATA
minkar-0.3.2.dist-info/WHEEL
minkar-0.3.2.dist-info/entry_points.txt
minkar-0.3.2.dist-info/top_level.txt
minkar-0.3.2.dist-info/RECORD
