Metadata-Version: 2.4
Name: minkar
Version: 0.3.2
Summary: A CLI toolkit to improve development workflow.
Author: Waland2
License: MIT License
Project-URL: Repository, https://github.com/Waland2/Minkar
Classifier: Programming Language :: Python :: 3
Classifier: License :: OSI Approved :: MIT License
Classifier: Operating System :: OS Independent
Requires-Python: >=3.9
License-File: LICENSE.md
Requires-Dist: typer[all]>=0.12
Requires-Dist: pyperclip>=1.8
Dynamic: license-file
